trag/__init__.py
trag/cli.hy
trag/retrieve.hy
trag/template.hy
trag/templates/latex.toml
trag/templates/retrieval.toml
trag/templates/summary.toml
trag-0.0.15.dist-info/licenses/LICENSE
trag-0.0.15.dist-info/METADATA
trag-0.0.15.dist-info/WHEEL
trag-0.0.15.dist-info/entry_points.txt
trag-0.0.15.dist-info/top_level.txt
trag-0.0.15.dist-info/RECORD
