Metadata-Version: 2.4
Name: trag
Version: 0.0.15
Summary: Simple templating and web-source retrieval utilities for RAG.
Author-email: Ati Sharma <ati+trag@agalmic.ltd>
License:                     GNU AFFERO GENERAL PUBLIC LICENSE
Project-URL: Repository, https://github.com/atisharma/trag
Keywords: hy,hylang,rag
Classifier: Development Status :: 4 - Beta
Classifier: License :: OSI Approved :: GNU Affero General Public License v3 or later (AGPLv3+)
Classifier: Programming Language :: Python :: 3
Classifier: Programming Language :: Python :: 3.11
Classifier: Programming Language :: Python :: 3.12
Classifier: Programming Language :: Python :: 3.13
Classifier: Programming Language :: Hy
Requires-Python: >=3.11
License-File: LICENSE
Requires-Dist: arxiv
Requires-Dist: click
Requires-Dist: ddgs
Requires-Dist: httpx
Requires-Dist: hy
Requires-Dist: hyjinx
Requires-Dist: hyrule
Requires-Dist: lxml
Requires-Dist: lxml_html_clean
Requires-Dist: markdownify
Requires-Dist: platformdirs
Requires-Dist: wikipedia
Requires-Dist: youtube-transcript-api>=1.2.2
Dynamic: license-file
